handler_reviews_lib/__init__.py
handler_reviews_lib/handler_reviews/__init__.py
handler_reviews_lib/handler_reviews/enums_type.py
handler_reviews_lib/handler_reviews/gpt_reviews_handler.py
handler_reviews_lib/handler_reviews/handler_reviews.py
handler_reviews_lib/handler_reviews/template_reviews_handler.py
handler_reviews_lib/interfaces/__init__.py
handler_reviews_lib/interfaces/interface_handler_reviews.py
handler_reviews_lib/interfaces/interface_reviews_handler_factory.py
handler_reviews_lib-1.1.2.dist-info/METADATA
handler_reviews_lib-1.1.2.dist-info/WHEEL
handler_reviews_lib-1.1.2.dist-info/top_level.txt
handler_reviews_lib-1.1.2.dist-info/RECORD
