Metadata-Version: 2.2
Name: handler_reviews_lib
Version: 1.1.2
Summary: This is the module for work with handlers of reviews by templates or GPT
Home-page: 
Author: 1mlnmyfavoriteinteger
Author-email: romansergeev7680@gmail.com
Project-URL: GitHub, https://github.com/Azakaim
Keywords: reviews,handler
Classifier: Programming Language :: Python :: 3.12
Classifier: License :: OSI Approved :: MIT License
Classifier: Operating System :: OS Independent
Requires-Python: >=3.6
Requires-Dist: requests>=2.25.1
Requires-Dist: openai>=1.40.3
Requires-Dist: httpx>=0.28.1
Requires-Dist: tiktoken>=0.7.0
Requires-Dist: pydantic>=2.8.2
Requires-Dist: setuptools>=72.1.0
Dynamic: author
Dynamic: author-email
Dynamic: classifier
Dynamic: description
Dynamic: description-content-type
Dynamic: keywords
Dynamic: project-url
Dynamic: requires-dist
Dynamic: requires-python
Dynamic: summary
